{
  "provider": "https://www.exchangerate-api.com",
  "WARNING_UPGRADE_TO_V6": "https://www.exchangerate-api.com/docs/free",
  "terms": "https://www.exchangerate-api.com/terms",
  "base": "HTG",
  "date": "2025-01-04",
  "time_last_updated": 1735948802,
  "rates": {
    "HTG": 1,
    "AED": 0.0281,
    "AFN": 0.539,
    "ALL": 0.722,
    "AMD": 3.04,
    "ANG": 0.0137,
    "AOA": 7.06,
    "ARS": 7.92,
    "AUD": 0.0123,
    "AWG": 0.0137,
    "AZN": 0.013,
    "BAM": 0.0144,
    "BBD": 0.0153,
    "BDT": 0.915,
    "BGN": 0.0144,
    "BHD": 0.00288,
    "BIF": 22.65,
    "BMD": 0.00765,
    "BND": 0.0104,
    "BOB": 0.053,
    "BRL": 0.0473,
    "BSD": 0.00765,
    "BTN": 0.655,
    "BWP": 0.107,
    "BYN": 0.0258,
    "BZD": 0.0153,
    "CAD": 0.011,
    "CDF": 21.85,
    "CHF": 0.00691,
    "CLP": 7.61,
    "CNY": 0.0559,
    "COP": 33.71,
    "CRC": 3.9,
    "CUP": 0.184,
    "CVE": 0.811,
    "CZK": 0.185,
    "DJF": 1.36,
    "DKK": 0.0549,
    "DOP": 0.468,
    "DZD": 1.04,
    "EGP": 0.389,
    "ERN": 0.115,
    "ETB": 0.978,
    "EUR": 0.00736,
    "FJD": 0.0179,
    "FKP": 0.0061,
    "FOK": 0.0549,
    "GBP": 0.0061,
    "GEL": 0.0215,
    "GGP": 0.0061,
    "GHS": 0.113,
    "GIP": 0.0061,
    "GMD": 0.555,
    "GNF": 65.89,
    "GTQ": 0.059,
    "GYD": 1.6,
    "HKD": 0.0594,
    "HNL": 0.195,
    "HRK": 0.0554,
    "HUF": 3.03,
    "IDR": 124.11,
    "ILS": 0.0279,
    "IMP": 0.0061,
    "INR": 0.655,
    "IQD": 10.03,
    "IRR": 326.32,
    "ISK": 1.06,
    "JEP": 0.0061,
    "JMD": 1.19,
    "JOD": 0.00543,
    "JPY": 1.2,
    "KES": 0.989,
    "KGS": 0.666,
    "KHR": 30.89,
    "KID": 0.0123,
    "KMF": 3.62,
    "KRW": 11.28,
    "KWD": 0.00236,
    "KYD": 0.00638,
    "KZT": 4.02,
    "LAK": 167.53,
    "LBP": 684.98,
    "LKR": 2.24,
    "LRD": 1.41,
    "LSL": 0.144,
    "LYD": 0.0376,
    "MAD": 0.0774,
    "MDL": 0.141,
    "MGA": 36.01,
    "MKD": 0.452,
    "MMK": 16.06,
    "MNT": 26.21,
    "MOP": 0.0612,
    "MRU": 0.305,
    "MUR": 0.36,
    "MVR": 0.118,
    "MWK": 13.27,
    "MXN": 0.158,
    "MYR": 0.0342,
    "MZN": 0.489,
    "NAD": 0.144,
    "NGN": 11.81,
    "NIO": 0.282,
    "NOK": 0.0867,
    "NPR": 1.05,
    "NZD": 0.0136,
    "OMR": 0.00294,
    "PAB": 0.00765,
    "PEN": 0.0288,
    "PGK": 0.0311,
    "PHP": 0.443,
    "PKR": 2.13,
    "PLN": 0.0314,
    "PYG": 60.12,
    "QAR": 0.0279,
    "RON": 0.0366,
    "RSD": 0.86,
    "RUB": 0.84,
    "RWF": 10.54,
    "SAR": 0.0287,
    "SBD": 0.065,
    "SCR": 0.111,
    "SDG": 4.17,
    "SEK": 0.0844,
    "SGD": 0.0104,
    "SHP": 0.0061,
    "SLE": 0.175,
    "SLL": 175.32,
    "SOS": 4.37,
    "SRD": 0.272,
    "SSP": 29.73,
    "STN": 0.18,
    "SYP": 99.17,
    "SZL": 0.144,
    "THB": 0.262,
    "TJS": 0.0834,
    "TMT": 0.0268,
    "TND": 0.0244,
    "TOP": 0.0185,
    "TRY": 0.27,
    "TTD": 0.052,
    "TVD": 0.0123,
    "TWD": 0.251,
    "TZS": 18.62,
    "UAH": 0.322,
    "UGX": 28.13,
    "USD": 0.00765,
    "UYU": 0.334,
    "UZS": 98.57,
    "VES": 0.406,
    "VND": 195.61,
    "VUV": 0.915,
    "WST": 0.0216,
    "XAF": 4.82,
    "XCD": 0.0207,
    "XDR": 0.0059,
    "XOF": 4.82,
    "XPF": 0.878,
    "YER": 1.91,
    "ZAR": 0.144,
    "ZMW": 0.213,
    "ZWL": 0.198
  }
}